LICENSE
MANIFEST.in
README.rst
setup.py
PyPeridyno.egg-info/PKG-INFO
PyPeridyno.egg-info/SOURCES.txt
PyPeridyno.egg-info/dependency_links.txt
PyPeridyno.egg-info/top_level.txt
src/PyPeridyno-1.2.0.exp
src/PyPeridyno-1.2.0.lib
src/PyPeridyno.pyd
src/dynoDualParticleSystem-1.2.0.dll
src/dynoFramework-1.2.0.dll
src/dynoGLRenderEngine-1.2.0.dll
src/dynoGlfwGUI-1.2.0.dll
src/dynoHeightField-1.2.0.dll
src/dynoIO-1.2.0.dll
src/dynoImWidgets-1.2.0.dll
src/dynoInteraction-1.2.0.dll
src/dynoModeling-1.2.0.dll
src/dynoMultiphysics-1.2.0.dll
src/dynoParticleSystem-1.2.0.dll
src/dynoPeridynamics-1.2.0.dll
src/dynoRenderCore-1.2.0.dll
src/dynoRigidBody-1.2.0.dll
src/dynoSemiAnalyticalScheme-1.2.0.dll
src/dynoTopology-1.2.0.dll
src/dynoVolume-1.2.0.dll
src/glad-2.0.0.dll
src/glfw3.dll
src/glslangValidator.exe
src/imgui-1.90.8.dll
src/plugin-ObjIO-1.2.0.dll
src/example/CodimensionalPD/CPD_ClothDrop.py
src/example/CodimensionalPD/CPD_ClothOnTable.py
src/example/CodimensionalPD/CPD_ClothOverBall_1.py
src/example/CodimensionalPD/CPD_ClothOverBall_3.py
src/example/CodimensionalPD/CPD_ClothOverBall_6.py
src/example/CodimensionalPD/CPD_RealTimeCloth_v1.py
src/example/CodimensionalPD/CPD_RealTimeCloth_v2.py
src/example/CodimensionalPD/CPD_RotateCylinder.py
src/example/CodimensionalPD/CPD_ShootingCloth.py
src/example/CodimensionalPD/GL_ClothWithCollision.py
src/example/DualParticle/DualParticle_4Box.py
src/example/DualParticle/DualParticle_CollidingFish.py
src/example/DualParticle/DualParticle_Fountain.py
src/example/DualParticle/DualParticle_Jets.py
src/example/DualParticle/Qt_DualParticle_FishAndBall.py
src/example/HeightField/GL_CapillaryWave.py
src/example/HeightField/GL_GranularMedia.py
src/example/HeightField/GL_Ocean.py
src/example/HeightField/GL_OceanPatch.py
src/example/HeightField/GL_RigidSandCoupling.py
src/example/HeightField/GL_Terrain.py
src/example/HeightField/Qt_Buoyancy.py
src/example/HeightField/Qt_LargeOcean.py
src/example/Modeling/Qt_GLTF.py
src/example/Modeling/Qt_GUI_ProcedureModeling.py
src/example/Modeling/Qt_JeepError.py
src/example/Modeling/Qt_JeepLandscape.py
