Metadata-Version: 2.4
Name: PyPeridyno
Version: 1.2.0
Summary: A python package for Peridyno
Home-page: https://peridyno.com/
Author: unibeam
Author-email: xiaowei@iscas.ac.cn
License: Apache License, Version 2.0
Classifier: Programming Language :: Python :: 3
Classifier: License :: OSI Approved :: Apache Software License
Classifier: Operating System :: Microsoft :: Windows
Classifier: Operating System :: POSIX :: Linux
Requires-Python: >=3.12
License-File: LICENSE
Dynamic: author
Dynamic: author-email
Dynamic: classifier
Dynamic: description
Dynamic: description-content-type
Dynamic: home-page
Dynamic: license
Dynamic: license-file
Dynamic: requires-python
Dynamic: summary
